typecast/__init__.py
typecast/async_client.py
typecast/client.py
typecast/conf.py
typecast/exceptions.py
typecast/sse.py
typecast/utils.py
typecast/websocket.py
typecast/models/__init__.py
typecast/models/error.py
typecast/models/tts.py
typecast/models/tts_wss.py
typecast/models/voices.py
typecast_python-0.1.3.dist-info/METADATA
typecast_python-0.1.3.dist-info/WHEEL
typecast_python-0.1.3.dist-info/licenses/LICENSE
typecast_python-0.1.3.dist-info/RECORD
