Metadata-Version: 2.4
Name: typecast-python
Version: 0.1.3
Summary: Official Typecast Python SDK - Convert text to lifelike speech using AI-powered voices
Project-URL: Homepage, https://typecast.ai
Project-URL: Documentation, https://typecast.ai/docs/overview
Project-URL: Repository, https://github.com/neosapience/typecast-python
Project-URL: Issues, https://github.com/neosapience/typecast-python/issues
Author-email: Neosapience <help@typecast.ai>
Maintainer-email: Neosapience <help@typecast.ai>
License:                                  Apache License
License-File: LICENSE
Keywords: ai,audio,speech-synthesis,text-to-speech,tts,typecast,voice,voice-generation
Classifier: Development Status :: 3 - Alpha
Classifier: Intended Audience :: Developers
Classifier: License :: OSI Approved :: Apache Software License
Classifier: Operating System :: OS Independent
Classifier: Programming Language :: Python :: 3
Classifier: Programming Language :: Python :: 3.11
Classifier: Programming Language :: Python :: 3.12
Classifier: Programming Language :: Python :: 3.13
Classifier: Topic :: Multimedia :: Sound/Audio :: Speech
Classifier: Topic :: Software Development :: Libraries :: Python Modules
Requires-Python: >=3.11
Requires-Dist: aiohttp>=3.8.0
Requires-Dist: pydantic>=2.0.0
Requires-Dist: requests>=2.28.0
Requires-Dist: sseclient-py>=1.7.2
Requires-Dist: typing-extensions>=4.0.0
Requires-Dist: websockets>=10.0
Provides-Extra: dev
Requires-Dist: black>=23.0.0; extra == 'dev'
Requires-Dist: flake8>=6.0.0; extra == 'dev'
Requires-Dist: isort>=5.0.0; extra == 'dev'
Requires-Dist: mypy>=1.0.0; extra == 'dev'
Requires-Dist: pytest-asyncio>=0.21.0; extra == 'dev'
Requires-Dist: pytest-mock>=3.14.0; extra == 'dev'
Requires-Dist: pytest>=7.0.0; extra == 'dev'
